rustyfim-0.2.2.dist-info/METADATA
rustyfim-0.2.2.dist-info/WHEEL
rustyfim/__init__.py
rustyfim/rustyfim.cpython-39-x86_64-linux-gnu.so
rustyfim-0.2.2.dist-info/RECORD
